setup.py
bzcache/__init__.py
bzcache/bz_cache_refresh.py
bzcache/bz_pulse_monitor.py
bzcache/bzcache.py
bzcache/bzload.py
bzcache/config.py
bzcache/daemon.py
bzcache.egg-info/PKG-INFO
bzcache.egg-info/SOURCES.txt
bzcache.egg-info/dependency_links.txt
bzcache.egg-info/not-zip-safe
bzcache.egg-info/requires.txt
bzcache.egg-info/top_level.txt