Metadata-Version: 1.0
Name: bzcache
Version: 0.1.1
Summary: Pulse-based bugzilla cache
Home-page: http://hg.mozilla.org/users/jgriffin_mozilla.com/bzcache/
Author: Jonathan Griffin
Author-email: jgriffin@mozilla.com
License: MPL
Platform: UNKNOWN
